claude_monitor/__init__.py
claude_monitor/__main__.py
claude_monitor/cli.py
claude_monitor/analyzers/__init__.py
claude_monitor/analyzers/configuration.py
claude_monitor/analyzers/features.py
claude_monitor/analyzers/integrations.py
claude_monitor/analyzers/project_analyzer.py
claude_monitor/analyzers/tokens.py
claude_monitor/analyzers/usage.py
claude_monitor/models/__init__.py
claude_monitor/parsers/__init__.py
claude_monitor/parsers/configuration_scanner.py
claude_monitor/parsers/debug.py
claude_monitor/parsers/files.py
claude_monitor/parsers/history.py
claude_monitor/parsers/sessions.py
claude_monitor/parsers/skills.py
claude_monitor/parsers/tools.py
claude_monitor/utils/__init__.py
claude_monitor/utils/paths.py
claude_monitor/utils/time_filter.py
claude_monitor/web/__init__.py
claude_monitor/web/app.py
claude_monitor/web/routes/__init__.py
claude_monitor/web/routes/api.py
claude_monitor/web/routes/charts.py
claude_monitor/web/routes/dashboard.py
claude_monitor/web/services/__init__.py
claude_monitor/web/services/chart_service.py
claude_monitor/web/services/dashboard_service.py
claude_monitor/web/static/css/.gitkeep
claude_monitor/web/static/js/.gitkeep
claude_monitor/web/templates/__init__.py
claude_monitor/web/templates/base.html
claude_monitor/web/templates/components/card.html
claude_monitor/web/templates/components/table.html
claude_monitor/web/templates/layouts/app.html
claude_monitor/web/templates/pages/__init__.py
claude_monitor/web/templates/pages/configuration.html
claude_monitor/web/templates/pages/dashboard.html
claude_monitor/web/templates/pages/error.html
claude_monitor/web/templates/pages/features.html
claude_monitor/web/templates/pages/files.html
claude_monitor/web/templates/pages/integrations.html
claude_monitor/web/templates/pages/projects.html
claude_monitor/web/templates/pages/tokens.html
claude_monitor/web/templates/partials/__init__.py
claude_monitor/web/templates/partials/cost_trend_charts.html
monitor_claude-1.0.5.dist-info/licenses/LICENSE
monitor_claude-1.0.5.dist-info/METADATA
monitor_claude-1.0.5.dist-info/WHEEL
monitor_claude-1.0.5.dist-info/entry_points.txt
monitor_claude-1.0.5.dist-info/top_level.txt
monitor_claude-1.0.5.dist-info/RECORD
