Metadata-Version: 2.4
Name: monitor-claude
Version: 1.0.5
Summary: Web-based usage monitoring tool for Claude Code
Author: Allan Napier
Requires-Python: >=3.9
License-File: LICENSE
Requires-Dist: click>=8.1.0
Requires-Dist: rich>=13.0.0
Requires-Dist: python-dateutil>=2.8.0
Requires-Dist: Flask>=3.0.0
Requires-Dist: Jinja2>=3.1.0
Dynamic: license-file
Dynamic: requires-python
